love_kbo-0.1.0.dist-info/METADATA
love_kbo-0.1.0.dist-info/WHEEL
love_kbo/__init__.py
love_kbo-0.1.0.dist-info/RECORD
